CHANGES
LICENSE
MANIFEST.in
README.rst
let.py
setup.py
let.egg-info/PKG-INFO
let.egg-info/SOURCES.txt
let.egg-info/dependency_links.txt
let.egg-info/top_level.txt